README.md
setup.py
data_code/__init__.py
data_code/airflow/__init__.py
data_code/airflow/general.py
data_code/airflow/raw/__init__.py
data_code/airflow/raw/utils.py
data_code/airflow/trn/__init__.py
data_code/airflow/trn/utils.py
data_code/airflow/wrk/__init__.py
data_code/airflow/wrk/utils.py
data_code/beam/__init__.py
data_code/beam/database.py
data_code/beam/processing.py
data_code/gcp/__init__.py
data_code/gcp/bq.py
data_code/gcp/secrets.py
data_code/gcp/service_account.py
data_code/gcp/sql.py
data_code/gcp/storage.py
data_code/parquets/__init__.py
data_code/parquets/get_schema.py
data_code/parquets/parquet2csv.py
data_code/utils/__init__.py
data_code/utils/appearence.py
data_code/utils/evaluate.py
data_code/utils/params.py
yastas_data.egg-info/PKG-INFO
yastas_data.egg-info/SOURCES.txt
yastas_data.egg-info/dependency_links.txt
yastas_data.egg-info/top_level.txt