Metadata-Version: 1.0
Name: yastas-data
Version: 1.3.0
Summary: Paquete distribuible en repositorio de funciones locales Data
Home-page: https://bitbucket.org/gentera-insumos/data-code
Author: Data - Aaron
Author-email: e-ajuareza@minsait.com
License: MIT
Keywords: data,big_data,data_analytics,data_engineer,data_science
Platform: UNKNOWN
